http_request_args/__init__.py
http_request_args/argument.py
http_request_args/arguments_params.py
http_request_args/arguments_prototypes.py
http_request_args/qs_parser.py
http_request_args/status.py
http_request_args/utilities.py
http_request_args/validation.py
http_request_args-0.1.31.dist-info/LICENSE
http_request_args-0.1.31.dist-info/METADATA
http_request_args-0.1.31.dist-info/WHEEL
http_request_args-0.1.31.dist-info/top_level.txt
http_request_args-0.1.31.dist-info/RECORD
