Metadata-Version: 2.1
Name: http-request-args
Version: 0.1.31
Summary: This library is to validate the request body and query string arguments. This library is implemented to be used with flask-restplus library.
Home-page: https://github.com/Quakingaspen-codehub/http-request-args
Author: Quaking Aspen
Author-email: info@quakingaspen.net
License: MIT
Platform: UNKNOWN
Classifier: Programming Language :: Python :: 3
Classifier: License :: OSI Approved :: MIT License
Classifier: Operating System :: OS Independent
Requires-Python: >=3.6
License-File: LICENSE
